Riscv_project/rtl/decoded_instr.svh
`ifndef decoded_instr_t_d
`define decoded_instr_t_d
    
// DECODED INSTRUCTION STRUCT
typedef struct packed {
    // Basic fields
    logic [6:0] opcode;
    logic [4:0] rd;
    logic [2:0] func3;
    logic [4:0] rs1;
    logic [4:0] rs2;
    logic [6:0] func7;
    // Immediates (already sign-extended)
    logic signed [31:0] imm_i;
    logic signed [31:0] imm_s;
    logic signed [31:0] imm_b;
    logic signed [31:0] imm_u;
    logic signed [31:0] imm_j;
    // Type flags (boolean)
    logic [0:0] is_r;
    logic [0:0] is_i;
    logic [0:0] is_s;
    logic [0:0] is_b;
    logic [0:0] is_u;
    logic [0:0] is_j;

} decoded_instr_t;

`endif

Riscv_project/rtl/alu.sv
`include "decoded_instr.svh"

module alu(
    input logic [0:0] clk,
    input logic [31:0] rs1,
    input logic [31:0] rs2,
    input decoded_instr_t instr,

    output logic [31:0] result
);

    always_comb begin

        logic [31:0] rs1_x = rs1;
        logic [31:0] rs2_x = (instr.is_r) ? rs2 : instr.imm_i;


        case (instr.func3)

            3'b000: result = (instr.func7 == 7'h20 ? rs1_x - rs2_x : rs1_x + rs2_x);
            3'b001: result = rs1_x << rs2_x;
            3'b010: result = (rs1_x < rs2_x) ? 1 : 0;
            3'b011: result = ({0,rs1_x} < {0,rs2_x} ? 1 : 0);
            3'b100: result = rs1_x ^ rs2_x;
            3'b101: result = (instr.func7 == 7'h20 ? rs1_x >> rs2_x : rs1_x >>> rs2_x);
            3'b110: result = rs1_x | rs2_x;
            3'b111: result = rs1_x & rs2_x;

        endcase
        
    end

endmodule

Riscv_project/rtl/reg_file.sv
module reg_file(
    input logic [0:0] clk,
    input logic [4:0] rs1_address,
    input logic [4:0] rs2_address,
    output logic [31:0] rs1_data,
    output logic [31:0] rs2_data,
    input logic [0:0] save_enable,
    input logic [4:0] save_address,
    input logic [31:0] save_value
);

    logic [31:0] block [31:0];


    always_comb begin
        
        rs1_data = block[rs1_address];
        rs2_data = block[rs2_address];

    end

    always @(posedge clk ) begin
        if (save_enable && save_address != 4'b0000)
            block[save_address] <= save_value;
    end


endmodule

Riscv_project/rtl/instruction_decoder.sv
`include "decoded_instr.svh"

module instruction_decoder(
    input logic [31:0] instruction,
    output decoded_instr_t mask,
    output logic [0:0] trap_instr
);

    always_comb begin                       

        // Breaking the instruction into its masks
        mask.opcode = instruction[6:0];
        mask.rd = instruction[11:7];
        mask.func3 = instruction[14:12];
        mask.rs1 = instruction[19:15];
        mask.rs2 = instruction[24:20];
        mask.func7 = instruction[31:25];

        // instruction type
        mask.is_r = (mask.opcode == 7'b0110011);
        mask.is_i = (mask.opcode == 7'b0010011) || (mask.opcode == 7'b0000011);
        mask.is_s = (mask.opcode == 7'b0100011);
        mask.is_b = (mask.opcode == 7'b1100011);
        mask.is_u = (mask.opcode == 7'b0110111) || (mask.opcode == 7'b0010111);
        mask.is_j = (mask.opcode == 7'b1101111);

        trap_instr = !(mask.is_r || mask.is_i || mask.is_s || mask.is_b || mask.is_u || mask.is_j);

        if (trap_instr)
            $display("Illegal opcode\n");

        // Immediates (ALREADY SIGNED)
        mask.imm_i= {{20{instruction[31]}} , instruction [31:20]};

        mask.imm_s = {{20{instruction[31]}}, instruction[31:25], instruction[11:7]};

        mask.imm_b = {{19{instruction[31]}}, instruction[31], instruction[7],
                   instruction[30:25], instruction[11:8], 1'b0};

        mask.imm_u = {instruction[31:12], 12'b0};

        mask.imm_j = {{11{instruction[31]}}, instruction[31],
                   instruction[19:12], instruction[20],
                   instruction[30:21], 1'b0};

    end                     

endmodule

Riscv_project/rtl/pc.sv
module pc (
    input logic [0:0] clk,
    input logic [0:0] reset,
    input logic [31:0] reset_address,
    input logic [0:0] stall,
    output logic [31:0] program_counter
);

    always @(posedge clk ) begin

        if (reset)
            program_counter <= reset_address;
        else if(!stall)
            program_counter <= program_counter + 32'h4;

    end

endmodule

Riscv_project/rtl/ram_controller.sv
module ram_controller(
    input logic[0:0] clk,

    input logic[31:0] pc,
    output logic[31:0] instruction,

    input logic[31:0] load_address,
    output logic[31:0] load_value,

    input logic[31:0] store_address,
    input logic[0:0] store_enabled,
    input logic[31:0] store_value,

    output logic[0:0] stall,

    output logic[0:0] trap_ram

);
    // Bram Block
    logic[31:0] bram_block[0:1023];

    // load program into block
    initial begin

        $readmemh("program.hex" , bram_block);
        $display("initialised program");

    end

    // Masking inputs for working logic
    wire [9:0] pc_idx = pc[11:2];
    wire [9:0] store_idx = load_address[11:2];
    wire [9:0] load_idx = store_address[11:2];

    always @(posedge clk ) begin
        if (store_enabled)
            bram_block[store_idx] <= store_value;

        load_value <= bram_block[load_idx];

        instruction <= bram_block[pc_idx];
    end


endmodule

Riscv_project/rtl/wrapper.sv
`include "decoded_instr.svh"

module wrapper (
    input logic[1:0] clk
);

    // PC
    logic[31:0] program_counter;

    // INSTRUCION
    logic[31:0] instruction;

    // DECODED INSTRUCTION
    decoded_instr_t decoded_instr;

    // RAM LOAD ARGS
    logic [31:0] ram_load_address;
    logic [31:0] ram_load_value;

    // RAM STORE ARGS
    logic [31:0] ram_store_address;
    logic [0:0] ram_store_enabled;
    logic [31:0] ram_store_value;

    // REGISTER LOAD ARGS
    logic [4:0] rs1_address = decoded_instr.rs1;
    logic [4:0] rs2_address = decoded_instr.rs2;
    logic [31:0] rs1_data;
    logic [31:0] rs2_data;
    
    // REGISTER STORE ARGS
    logic [0:0] reg_save_enable = !(decoded_instr.is_s || decoded_instr.is_b);
    logic [4:0] reg_save_address = decoded_instr.rd;
    logic [31:0] reg_save_value = (decoded_instr.is_r == 1'b1) ? alu_output : 32'h00000000;

    // ALU OUTPUT
    logic [31:0] alu_output;

    // CPU STALL
    logic [0:0] stall;

    // TRAPS
    logic [0:0] ram_trap;

    // PC RESET
    logic [0:0] reset;
    logic [31:0] reset_address;

    ram_controller ram_controller(
        clk,
        program_counter,
        instruction,
        ram_load_address,
        ram_load_value,
        ram_store_address,
        ram_store_enabled,
        ram_store_value,
        stall,
        ram_trap
    );

    pc pc(
        clk,
        reset,
        reset_address,
        stall,
        program_counter
    );

    instruction_decoder instruction_decoder(
        instruction,
        decoded_instr
    );

    reg_file reg_file(
        clk,
        rs1_address,
        rs2_address,
        rs1_data,
        rs2_data,
        reg_save_enable,
        reg_save_address,
        reg_save_value
    );

    alu alu(
        clk,
        rs1_data,
        rs2_data,
        decoded_instr,
        alu_output
    );

endmodule

Riscv_project/rtl/test_.sv
`timescale 1ns/1ns


module test_ ();

    logic clk = 0;

    wrapper wrapper(clk);

    initial begin

        $display("Begin");

        $dumpfile("wave.vcd");
        $dumpvars(0, test_);

        repeat (100) begin
            #1 clk = 1;
            #1 clk = 0;
        end

        $finish;

    end


endmodule

Riscv_project/wave.vcd
$version Generated by VerilatedVcd $end
$timescale 1ns $end
 $scope module TOP $end
  $scope module test_ $end
   $var wire 1 Y clk $end
   $scope module wrapper $end
    $var wire 2 Z clk [1:0] $end
    $var wire 32 # program_counter [31:0] $end
    $var wire 32 $ instruction [31:0] $end
    $var wire 198 % decoded_instr [197:0] $end
    $var wire 32 [ ram_load_address [31:0] $end
    $var wire 32 , ram_load_value [31:0] $end
    $var wire 32 \ ram_store_address [31:0] $end
    $var wire 1 ] ram_store_enabled [0:0] $end
    $var wire 32 ^ ram_store_value [31:0] $end
    $var wire 5 - rs1_address [4:0] $end
    $var wire 5 . rs2_address [4:0] $end
    $var wire 32 / rs1_data [31:0] $end
    $var wire 32 0 rs2_data [31:0] $end
    $var wire 1 1 reg_save_enable [0:0] $end
    $var wire 5 2 reg_save_address [4:0] $end
    $var wire 32 3 reg_save_value [31:0] $end
    $var wire 32 4 alu_output [31:0] $end
    $var wire 1 _ stall [0:0] $end
    $var wire 1 ` ram_trap [0:0] $end
    $var wire 1 a reset [0:0] $end
    $var wire 32 b reset_address [31:0] $end
    $scope module alu $end
     $var wire 1 Y clk [0:0] $end
     $var wire 32 / rs1 [31:0] $end
     $var wire 32 0 rs2 [31:0] $end
     $var wire 198 % instr [197:0] $end
     $var wire 32 4 result [31:0] $end
     $scope module unnamedblk1 $end
      $var wire 32 5 rs1_x [31:0] $end
      $var wire 32 6 rs2_x [31:0] $end
     $upscope $end
    $upscope $end
    $scope module instruction_decoder $end
     $var wire 32 $ instruction [31:0] $end
     $var wire 198 % mask [197:0] $end
     $var wire 1 7 trap_instr [0:0] $end
    $upscope $end
    $scope module pc $end
     $var wire 1 Y clk [0:0] $end
     $var wire 1 a reset [0:0] $end
     $var wire 32 b reset_address [31:0] $end
     $var wire 1 _ stall [0:0] $end
     $var wire 32 # program_counter [31:0] $end
    $upscope $end
    $scope module ram_controller $end
     $var wire 1 Y clk [0:0] $end
     $var wire 32 # pc [31:0] $end
     $var wire 32 $ instruction [31:0] $end
     $var wire 32 [ load_address [31:0] $end
     $var wire 32 , load_value [31:0] $end
     $var wire 32 \ store_address [31:0] $end
     $var wire 1 ] store_enabled [0:0] $end
     $var wire 32 ^ store_value [31:0] $end
     $var wire 1 _ stall [0:0] $end
     $var wire 1 ` trap_ram [0:0] $end
     $var wire 10 8 pc_idx [9:0] $end
     $var wire 10 c store_idx [9:0] $end
     $var wire 10 d load_idx [9:0] $end
    $upscope $end
    $scope module reg_file $end
     $var wire 1 Y clk [0:0] $end
     $var wire 5 - rs1_address [4:0] $end
     $var wire 5 . rs2_address [4:0] $end
     $var wire 32 / rs1_data [31:0] $end
     $var wire 32 0 rs2_data [31:0] $end
     $var wire 1 1 save_enable [0:0] $end
     $var wire 5 2 save_address [4:0] $end
     $var wire 32 3 save_value [31:0] $end
     $var wire 32 9 block[0] [31:0] $end
     $var wire 32 : block[1] [31:0] $end
     $var wire 32 ; block[2] [31:0] $end
     $var wire 32 < block[3] [31:0] $end
     $var wire 32 = block[4] [31:0] $end
     $var wire 32 > block[5] [31:0] $end
     $var wire 32 ? block[6] [31:0] $end
     $var wire 32 @ block[7] [31:0] $end
     $var wire 32 A block[8] [31:0] $end
     $var wire 32 B block[9] [31:0] $end
     $var wire 32 C block[10] [31:0] $end
     $var wire 32 D block[11] [31:0] $end
     $var wire 32 E block[12] [31:0] $end
     $var wire 32 F block[13] [31:0] $end
     $var wire 32 G block[14] [31:0] $end
     $var wire 32 H block[15] [31:0] $end
     $var wire 32 I block[16] [31:0] $end
     $var wire 32 J block[17] [31:0] $end
     $var wire 32 K block[18] [31:0] $end
     $var wire 32 L block[19] [31:0] $end
     $var wire 32 M block[20] [31:0] $end
     $var wire 32 N block[21] [31:0] $end
     $var wire 32 O block[22] [31:0] $end
     $var wire 32 P block[23] [31:0] $end
     $var wire 32 Q block[24] [31:0] $end
     $var wire 32 R block[25] [31:0] $end
     $var wire 32 S block[26] [31:0] $end
     $var wire 32 T block[27] [31:0] $end
     $var wire 32 U block[28] [31:0] $end
     $var wire 32 V block[29] [31:0] $end
     $var wire 32 W block[30] [31:0] $end
     $var wire 32 X block[31] [31:0] $end
    $upscope $end
   $upscope $end
  $upscope $end
 $upscope $end
$enddefinitions $end


#0
b00000000000000000000000000000000 #
b00000000000000000000000000000000 $
b000000000000000000000000000000000000000000000000000000000000000000000000000000000000000000000000000000000000000000000000000000000000000000000000000000000000000000000000000000000000000000000000000000 %
b00000000000000000000000000000000 ,
b00000 -
b00000 .
b00000000000000000000000000000000 /
b00000000000000000000000000000000 0
11
b00000 2
b00000000000000000000000000000000 3
b00000000000000000000000000000000 4
b00000000000000000000000000000000 5
b00000000000000000000000000000000 6
17
b0000000000 8
b00000000000000000000000000000000 9
b00000000000000000000000000000000 :
b00000000000000000000000000000000 ;
b00000000000000000000000000000000 <
b00000000000000000000000000000000 =
b00000000000000000000000000000000 >
b00000000000000000000000000000000 ?
b00000000000000000000000000000000 @
b00000000000000000000000000000000 A
b00000000000000000000000000000000 B
b00000000000000000000000000000000 C
b00000000000000000000000000000000 D
b00000000000000000000000000000000 E
b00000000000000000000000000000000 F
b00000000000000000000000000000000 G
b00000000000000000000000000000000 H
b00000000000000000000000000000000 I
b00000000000000000000000000000000 J
b00000000000000000000000000000000 K
b00000000000000000000000000000000 L
b00000000000000000000000000000000 M
b00000000000000000000000000000000 N
b00000000000000000000000000000000 O
b00000000000000000000000000000000 P
b00000000000000000000000000000000 Q
b00000000000000000000000000000000 R
b00000000000000000000000000000000 S
b00000000000000000000000000000000 T
b00000000000000000000000000000000 U
b00000000000000000000000000000000 V
b00000000000000000000000000000000 W
b00000000000000000000000000000000 X
0Y
b00 Z
b00000000000000000000000000000000 [
b00000000000000000000000000000000 \
0]
b00000000000000000000000000000000 ^
0_
0`
0a
b00000000000000000000000000000000 b
b0000000000 c
b0000000000 d
#1
b00000000000000000000000000000100 #
b0000000001 8
1Y
b01 Z
#2
0Y
b00 Z
#3
b00000000000000000000000000001000 #
b0000000010 8
1Y
b01 Z
#4
0Y
b00 Z
#5
b00000000000000000000000000001100 #
b0000000011 8
1Y
b01 Z
#6
0Y
b00 Z
#7
b00000000000000000000000000010000 #
b0000000100 8
1Y
b01 Z
#8
0Y
b00 Z
#9
b00000000000000000000000000010100 #
b0000000101 8
1Y
b01 Z
#10
0Y
b00 Z
#11
b00000000000000000000000000011000 #
b0000000110 8
1Y
b01 Z
#12
0Y
b00 Z
#13
b00000000000000000000000000011100 #
b0000000111 8
1Y
b01 Z
#14
0Y
b00 Z
#15
b00000000000000000000000000100000 #
b0000001000 8
1Y
b01 Z
#16
0Y
b00 Z
#17
b00000000000000000000000000100100 #
b0000001001 8
1Y
b01 Z
#18
0Y
b00 Z
#19
b00000000000000000000000000101000 #
b0000001010 8
1Y
b01 Z
#20
0Y
b00 Z
#21
b00000000000000000000000000101100 #
b0000001011 8
1Y
b01 Z
#22
0Y
b00 Z
#23
b00000000000000000000000000110000 #
b0000001100 8
1Y
b01 Z
#24
0Y
b00 Z
#25
b00000000000000000000000000110100 #
b0000001101 8
1Y
b01 Z
#26
0Y
b00 Z
#27
b00000000000000000000000000111000 #
b0000001110 8
1Y
b01 Z
#28
0Y
b00 Z
#29
b00000000000000000000000000111100 #
b0000001111 8
1Y
b01 Z
#30
0Y
b00 Z
#31
b00000000000000000000000001000000 #
b0000010000 8
1Y
b01 Z
#32
0Y
b00 Z
#33
b00000000000000000000000001000100 #
b0000010001 8
1Y
b01 Z
#34
0Y
b00 Z
#35
b00000000000000000000000001001000 #
b0000010010 8
1Y
b01 Z
#36
0Y
b00 Z
#37
b00000000000000000000000001001100 #
b0000010011 8
1Y
b01 Z
#38
0Y
b00 Z
#39
b00000000000000000000000001010000 #
b0000010100 8
1Y
b01 Z
#40
0Y
b00 Z
#41
b00000000000000000000000001010100 #
b0000010101 8
1Y
b01 Z
#42
0Y
b00 Z
#43
b00000000000000000000000001011000 #
b0000010110 8
1Y
b01 Z
#44
0Y
b00 Z
#45
b00000000000000000000000001011100 #
b0000010111 8
1Y
b01 Z
#46
0Y
b00 Z
#47
b00000000000000000000000001100000 #
b0000011000 8
1Y
b01 Z
#48
0Y
b00 Z
#49
b00000000000000000000000001100100 #
b0000011001 8
1Y
b01 Z
#50
0Y
b00 Z
#51
b00000000000000000000000001101000 #
b0000011010 8
1Y
b01 Z
#52
0Y
b00 Z
#53
b00000000000000000000000001101100 #
b0000011011 8
1Y
b01 Z
#54
0Y
b00 Z
#55
b00000000000000000000000001110000 #
b0000011100 8
1Y
b01 Z
#56
0Y
b00 Z
#57
b00000000000000000000000001110100 #
b0000011101 8
1Y
b01 Z
#58
0Y
b00 Z
#59
b00000000000000000000000001111000 #
b0000011110 8
1Y
b01 Z
#60
0Y
b00 Z
#61
b00000000000000000000000001111100 #
b0000011111 8
1Y
b01 Z
#62
0Y
b00 Z
#63
b00000000000000000000000010000000 #
b0000100000 8
1Y
b01 Z
#64
0Y
b00 Z
#65
b00000000000000000000000010000100 #
b0000100001 8
1Y
b01 Z
#66
0Y
b00 Z
#67
b00000000000000000000000010001000 #
b0000100010 8
1Y
b01 Z
#68
0Y
b00 Z
#69
b00000000000000000000000010001100 #
b0000100011 8
1Y
b01 Z
#70
0Y
b00 Z
#71
b00000000000000000000000010010000 #
b0000100100 8
1Y
b01 Z
#72
0Y
b00 Z
#73
b00000000000000000000000010010100 #
b0000100101 8
1Y
b01 Z
#74
0Y
b00 Z
#75
b00000000000000000000000010011000 #
b0000100110 8
1Y
b01 Z
#76
0Y
b00 Z
#77
b00000000000000000000000010011100 #
b0000100111 8
1Y
b01 Z
#78
0Y
b00 Z
#79
b00000000000000000000000010100000 #
b0000101000 8
1Y
b01 Z
#80
0Y
b00 Z
#81
b00000000000000000000000010100100 #
b0000101001 8
1Y
b01 Z
#82
0Y
b00 Z
#83
b00000000000000000000000010101000 #
b0000101010 8
1Y
b01 Z
#84
0Y
b00 Z
#85
b00000000000000000000000010101100 #
b0000101011 8
1Y
b01 Z
#86
0Y
b00 Z
#87
b00000000000000000000000010110000 #
b0000101100 8
1Y
b01 Z
#88
0Y
b00 Z
#89
b00000000000000000000000010110100 #
b0000101101 8
1Y
b01 Z
#90
0Y
b00 Z
#91
b00000000000000000000000010111000 #
b0000101110 8
1Y
b01 Z
#92
0Y
b00 Z
#93
b00000000000000000000000010111100 #
b0000101111 8
1Y
b01 Z
#94
0Y
b00 Z
#95
b00000000000000000000000011000000 #
b0000110000 8
1Y
b01 Z
#96
0Y
b00 Z
#97
b00000000000000000000000011000100 #
b0000110001 8
1Y
b01 Z
#98
0Y
b00 Z
#99
b00000000000000000000000011001000 #
b0000110010 8
1Y
b01 Z
#100
0Y
b00 Z
#101
b00000000000000000000000011001100 #
b0000110011 8
1Y
b01 Z
#102
0Y
b00 Z
#103
b00000000000000000000000011010000 #
b0000110100 8
1Y
b01 Z
#104
0Y
b00 Z
#105
b00000000000000000000000011010100 #
b0000110101 8
1Y
b01 Z
#106
0Y
b00 Z
#107
b00000000000000000000000011011000 #
b0000110110 8
1Y
b01 Z
#108
0Y
b00 Z
#109
b00000000000000000000000011011100 #
b0000110111 8
1Y
b01 Z
#110
0Y
b00 Z
#111
b00000000000000000000000011100000 #
b0000111000 8
1Y
b01 Z
#112
0Y
b00 Z
#113
b00000000000000000000000011100100 #
b0000111001 8
1Y
b01 Z
#114
0Y
b00 Z
#115
b00000000000000000000000011101000 #
b0000111010 8
1Y
b01 Z
#116
0Y
b00 Z
#117
b00000000000000000000000011101100 #
b0000111011 8
1Y
b01 Z
#118
0Y
b00 Z
#119
b00000000000000000000000011110000 #
b0000111100 8
1Y
b01 Z
#120
0Y
b00 Z
#121
b00000000000000000000000011110100 #
b0000111101 8
1Y
b01 Z
#122
0Y
b00 Z
#123
b00000000000000000000000011111000 #
b0000111110 8
1Y
b01 Z
#124
0Y
b00 Z
#125
b00000000000000000000000011111100 #
b0000111111 8
1Y
b01 Z
#126
0Y
b00 Z
#127
b00000000000000000000000100000000 #
b0001000000 8
1Y
b01 Z
#128
0Y
b00 Z
#129
b00000000000000000000000100000100 #
b0001000001 8
1Y
b01 Z
#130
0Y
b00 Z
#131
b00000000000000000000000100001000 #
b0001000010 8
1Y
b01 Z
#132
0Y
b00 Z
#133
b00000000000000000000000100001100 #
b0001000011 8
1Y
b01 Z
#134
0Y
b00 Z
#135
b00000000000000000000000100010000 #
b0001000100 8
1Y
b01 Z
#136
0Y
b00 Z
#137
b00000000000000000000000100010100 #
b0001000101 8
1Y
b01 Z
#138
0Y
b00 Z
#139
b00000000000000000000000100011000 #
b0001000110 8
1Y
b01 Z
#140
0Y
b00 Z
#141
b00000000000000000000000100011100 #
b0001000111 8
1Y
b01 Z
#142
0Y
b00 Z
#143
b00000000000000000000000100100000 #
b0001001000 8
1Y
b01 Z
#144
0Y
b00 Z
#145
b00000000000000000000000100100100 #
b0001001001 8
1Y
b01 Z
#146
0Y
b00 Z
#147
b00000000000000000000000100101000 #
b0001001010 8
1Y
b01 Z
#148
0Y
b00 Z
#149
b00000000000000000000000100101100 #
b0001001011 8
1Y
b01 Z
#150
0Y
b00 Z
#151
b00000000000000000000000100110000 #
b0001001100 8
1Y
b01 Z
#152
0Y
b00 Z
#153
b00000000000000000000000100110100 #
b0001001101 8
1Y
b01 Z
#154
0Y
b00 Z
#155
b00000000000000000000000100111000 #
b0001001110 8
1Y
b01 Z
#156
0Y
b00 Z
#157
b00000000000000000000000100111100 #
b0001001111 8
1Y
b01 Z
#158
0Y
b00 Z
#159
b00000000000000000000000101000000 #
b0001010000 8
1Y
b01 Z
#160
0Y
b00 Z
#161
b00000000000000000000000101000100 #
b0001010001 8
1Y
b01 Z
#162
0Y
b00 Z
#163
b00000000000000000000000101001000 #
b0001010010 8
1Y
b01 Z
#164
0Y
b00 Z
#165
b00000000000000000000000101001100 #
b0001010011 8
1Y
b01 Z
#166
0Y
b00 Z
#167
b00000000000000000000000101010000 #
b0001010100 8
1Y
b01 Z
#168
0Y
b00 Z
#169
b00000000000000000000000101010100 #
b0001010101 8
1Y
b01 Z
#170
0Y
b00 Z
#171
b00000000000000000000000101011000 #
b0001010110 8
1Y
b01 Z
#172
0Y
b00 Z
#173
b00000000000000000000000101011100 #
b0001010111 8
1Y
b01 Z
#174
0Y
b00 Z
#175
b00000000000000000000000101100000 #
b0001011000 8
1Y
b01 Z
#176
0Y
b00 Z
#177
b00000000000000000000000101100100 #
b0001011001 8
1Y
b01 Z
#178
0Y
b00 Z
#179
b00000000000000000000000101101000 #
b0001011010 8
1Y
b01 Z
#180
0Y
b00 Z
#181
b00000000000000000000000101101100 #
b0001011011 8
1Y
b01 Z
#182
0Y
b00 Z
#183
b00000000000000000000000101110000 #
b0001011100 8
1Y
b01 Z
#184
0Y
b00 Z
#185
b00000000000000000000000101110100 #
b0001011101 8
1Y
b01 Z
#186
0Y
b00 Z
#187
b00000000000000000000000101111000 #
b0001011110 8
1Y
b01 Z
#188
0Y
b00 Z
#189
b00000000000000000000000101111100 #
b0001011111 8
1Y
b01 Z
#190
0Y
b00 Z
#191
b00000000000000000000000110000000 #
b0001100000 8
1Y
b01 Z
#192
0Y
b00 Z
#193
b00000000000000000000000110000100 #
b0001100001 8
1Y
b01 Z
#194
0Y
b00 Z
#195
b00000000000000000000000110001000 #
b0001100010 8
1Y
b01 Z
#196
0Y
b00 Z
#197
b00000000000000000000000110001100 #
b0001100011 8
1Y
b01 Z
#198
0Y
b00 Z
#199
b00000000000000000000000110010000 #
b0001100100 8
1Y
b01 Z
#200
0Y
b00 Z
