Riscv_project/rtl/decoded_instr.svh
`ifndef decoded_instr_t_d
`define decoded_instr_t_d
    
// DECODED INSTRUCTION STRUCT
typedef struct packed {
    // Basic fields
    logic [6:0] opcode;
    logic [4:0] rd;
    logic [2:0] func3;
    logic [4:0] rs1;
    logic [4:0] rs2;
    logic [6:0] func7;
    // Immediates (already sign-extended)
    logic signed [31:0] imm_i;
    logic signed [31:0] imm_s;
    logic signed [31:0] imm_b;
    logic signed [31:0] imm_u;
    logic signed [31:0] imm_j;
    // Type flags (boolean)
    logic [0:0] is_r;
    logic [0:0] is_i;
    logic [0:0] is_s;
    logic [0:0] is_b;
    logic [0:0] is_u;
    logic [0:0] is_j;
    logic [0:0] is_jalr;

} decoded_instr_t;

`endif

Riscv_project/rtl/jump.sv
`include "decoded_instr.svh"

module jump(
    input decoded_instr_t instr,
    input logic [31:0] rs1_data,
    input logic [31:0] program_counter,
    output logic [31:0] reg_save_value,
    output logic [31:0] pc_save_value,
    output logic [0:0] pc_reset_jump
);

    always_comb begin

        reg_save_value = (instr.is_j == 1'b1 || instr.is_jalr == 1'b1 ? program_counter + 3'b100 : 32'h00000000);
        
        pc_save_value = (instr.is_j == 1'b1 ? program_counter + instr.imm_j 
        : (instr.is_jalr == 1'b1 ? instr.imm_i + rs1_data : 32'h00000000));
        
        pc_reset_jump = (instr.is_j || instr.is_jalr);

    end

endmodule

Riscv_project/rtl/branch.sv
`include "decoded_instr.svh"

module branch(
    input logic [31:0] rs1_data,
    input logic [31:0] rs2_data,
    input decoded_instr_t instr,
    input logic [31:0] pc,

    output logic [0:0] pc_reset_branch,
    output logic [31:0] reset_address
);


    always_comb begin

        logic unsigned [31:0] rs1_data_unsigned = rs1_data;
        logic unsigned [31:0] rs2_data_unsigned = rs2_data;

        pc_reset_branch = (
        ((rs1_data == rs2_data) && instr.func3 == 3'b000) ||

        ((rs1_data != rs2_data) && instr.func3 == 3'b001) ||

        ((rs1_data < rs2_data) && instr.func3 == 3'b100) ||

        ((rs1_data >= rs2_data) && instr.func3 == 3'b101) ||

        ((rs1_data_unsigned < rs2_data_unsigned) && instr.func3 == 3'b110) ||

        ((rs1_data_unsigned >= rs2_data_unsigned) && instr.func3 == 3'b111) ) && instr.is_b;
        
        reset_address = (pc_reset_branch == 1'b1 ? pc + instr.imm_b : 0);
    end

endmodule

Riscv_project/rtl/alu.sv
`include "decoded_instr.svh"

module alu(
    input logic [0:0] clk,
    input logic [31:0] rs1,
    input logic [31:0] rs2,
    input decoded_instr_t instr,

    output logic [31:0] result
);

    always_comb begin

        logic [31:0] rs1_x = rs1;
        logic [31:0] rs2_x = (instr.is_r) ? rs2 : (instr.func3 == 3'b101 || instr.func3 == 3'b001 ? instr.imm_i & 5'b1111 : instr.imm_i);

        case (instr.func3)

            3'b000: result = (instr.func7 == 7'h20 ? rs1_x - rs2_x : rs1_x + rs2_x);
            3'b001: result = rs1_x << rs2_x;
            3'b010: result = (rs1_x < rs2_x) ? 1 : 0;
            3'b011: result = ({0,rs1_x} < {0,rs2_x} ? 1 : 0);
            3'b100: result = rs1_x ^ rs2_x;
            3'b101: result = (instr.func7 == 7'h20 ? rs1_x >> rs2_x : rs1_x >>> rs2_x);
            3'b110: result = rs1_x | rs2_x;
            3'b111: result = rs1_x & rs2_x;

        endcase
        
    end

endmodule

Riscv_project/rtl/reg_file.sv
module reg_file(
    input logic [0:0] clk,
    input logic [4:0] rs1_address,
    input logic [4:0] rs2_address,
    output logic [31:0] rs1_data,
    output logic [31:0] rs2_data,
    input logic [0:0] save_enable,
    input logic [4:0] save_address,
    input logic [31:0] save_value
);

    logic [31:0] block [31:0];


    always_comb begin
        
        rs1_data = block[rs1_address];
        rs2_data = block[rs2_address];

    end

    always @(posedge clk ) begin
        if (save_enable && save_address != 4'b0000)
            block[save_address] <= save_value;
    end


endmodule

Riscv_project/rtl/instruction_decoder.sv
`include "decoded_instr.svh"

module instruction_decoder(
    input logic [31:0] instruction,
    output decoded_instr_t mask,
    output logic [0:0] trap_instr,
    input logic [0:0] clk,
    input logic [31:0] pc, // ONLY FOR DEBUGGING
    input logic [31:0] global_counter // ONLY FOR DEBUGGING
);

    always_comb begin                       

        logic[6:0] opcode = mask.opcode;
        logic[11:7] rd = mask.rd;
        logic[14:12] func3 = mask.func3;
        logic[19:15] rs1 = mask.rs1;
        logic[24:20] rs2 = mask.rs2;
        logic[31:25] func7 = mask.func7;

        logic[0:0] is_r = mask.is_r;
        logic[0:0] is_i = mask.is_i;
        logic[0:0] is_s = mask.is_s;
        logic[0:0] is_b = mask.is_b;
        logic[0:0] is_u = mask.is_u;
        logic[0:0] is_j = mask.is_j;

        // Breaking the instruction into its masks
        mask.opcode = instruction[6:0];
        mask.rd = instruction[11:7];
        mask.func3 = instruction[14:12];
        mask.rs1 = instruction[19:15];
        mask.rs2 = instruction[24:20];
        mask.func7 = instruction[31:25];

        // instruction type
        mask.is_r = (mask.opcode == 7'b0110011);
        mask.is_i = (mask.opcode == 7'b0010011) || (mask.opcode == 7'b0000011);
        mask.is_s = (mask.opcode == 7'b0100011);
        mask.is_b = (mask.opcode == 7'b1100011);
        mask.is_u = (mask.opcode == 7'b0110111) || (mask.opcode == 7'b0010111);
        mask.is_j = (mask.opcode == 7'b1101111);
        mask.is_jalr = (mask.opcode == 7'b1100111);

        trap_instr = !(mask.is_r || mask.is_i || mask.is_s || mask.is_b || mask.is_u || mask.is_j || mask.is_jalr);

        // Immediates (ALREADY SIGNED)
        mask.imm_i= {{20{instruction[31]}} , instruction [31:20]};

        mask.imm_s = {{20{instruction[31]}}, instruction[31:25], instruction[11:7]};

        mask.imm_b = {{19{instruction[31]}}, instruction[31], instruction[7],
                   instruction[30:25], instruction[11:8], 1'b0};

        mask.imm_u = {instruction[31:12], 12'b0};

        mask.imm_j = {{11{instruction[31]}}, instruction[31],
                   instruction[19:12], instruction[20],
                   instruction[30:21], 1'b0};

    end                     

    always @(posedge clk ) begin
        if (trap_instr)
            $display("Illegal opcode: %d , address: %d , global counter: %d \n" , mask.opcode , pc , global_counter);

    end

endmodule

Riscv_project/rtl/pc.sv
module pc (
    input logic [0:0] clk,
    input logic [0:0] reset,
    input logic [31:0] reset_address,
    input logic [0:0] stall,
    output logic [31:0] program_counter
);

    logic [31:0] current_counter; 

    always @(negedge clk ) begin        
        if (reset)
            current_counter <= reset_address;
        else if(!stall)
            current_counter <= current_counter + 32'h4;
    end

    always @(posedge clk) begin

        program_counter <= current_counter;

    end

endmodule

Riscv_project/rtl/ram_controller.sv
module ram_controller(
    input logic [0:0] clk,

    input logic [31:0] pc,
    output logic [31:0] instruction,
    input logic [2:0] func3,

    input logic [31:0] load_address,
    output logic [31:0] load_value,

    input logic [31:0] store_address,
    input logic [0:0] store_enabled,
    input logic [31:0] store_value,

    output logic [0:0] stall,

    output logic [0:0] trap_ram

);
    // Bram Block
    logic[31:0] bram_block[0:1023];

    // load program into block
    initial begin

        $readmemh("program.hex" , bram_block);
        $display("initialised program");

    end

    // Masking inputs for working logic
    wire [9:0] pc_idx = pc[11:2];
    wire [9:0] store_idx = load_address[11:2];
    wire [9:0] load_idx = store_address[11:2];

    always_comb begin
        load_value <= bram_block[load_idx];

        instruction <= bram_block[pc_idx];
    end

    always @(posedge clk ) begin
        if (store_enabled && func3 == 3'b010)
            bram_block[store_idx] <= store_value;

        if (store_enabled && func3 == 3'b001)
            bram_block[store_idx][15:0] <= store_value[15:0];

        if (store_enabled && func3 == 3'b000)
            bram_block[store_idx][7:0] <= store_value[7:0];
    end


endmodule

Riscv_project/rtl/wrapper.sv
`include "decoded_instr.svh"

module wrapper (
    input logic [1:0] clk
);

    // GLOBAL_COUNTER
    logic [31:0] global_counter;
    always @(posedge clk ) begin
        global_counter = global_counter + 3'b100;
    end

    // PC
    logic [31:0] program_counter;

    // INSTRUCION
    logic [31:0] instruction;

    // DECODED INSTRUCTION
    decoded_instr_t decoded_instr;

    // RAM LOAD ARGS
    logic [31:0] ram_load_address;
    logic [31:0] ram_load_value;

    // RAM STORE ARGS
    logic [31:0] ram_store_address = rs1_data + decoded_instr.imm_s;
    logic [0:0] ram_store_enabled = decoded_instr.is_s;
    logic [31:0] ram_store_value = rs2_data;

    // REGISTER LOAD ARGS
    logic [4:0] rs1_address = decoded_instr.rs1;
    logic [4:0] rs2_address = decoded_instr.rs2;
    logic [31:0] rs1_data;
    logic [31:0] rs2_data;
    
    // REGISTER STORE ARGS
    logic [0:0] reg_save_enable = !(decoded_instr.is_s || decoded_instr.is_b);
    logic [4:0] reg_save_address = decoded_instr.rd;
    logic [31:0] reg_save_value = (decoded_instr.is_r == 1'b1 || decoded_instr.is_i == 1'b1) ? alu_output
    : (pc_reset_jump == 1'b1 ? register_save_jump 
    : (decoded_instr.is_u == 1'b1 ? (decoded_instr.opcode == 7'b0110111 ? decoded_instr.imm_u : decoded_instr.imm_u + program_counter) 
    : 32'h00000000));

    // ALU OUTPUT
    logic [31:0] alu_output;

    // CPU STALL
    logic [0:0] stall;

    // TRAPS
    logic [0:0] ram_trap;
    logic [0:0] instruction_trap;

    // PC RESET
    logic [0:0] pc_reset = (pc_reset_branch || pc_reset_jump);
    logic [31:0] reset_address = (pc_reset_branch == 1'b1 ? reset_address_branch : (pc_reset_jump == 1'b1 ? pc_reset_address_jump : 32'h00000000));

    // BRANCH
    logic [0:0] pc_reset_branch;
    logic [31:0] reset_address_branch;

    // JUMP
    logic [0:0] pc_reset_jump;
    logic [31:0] pc_reset_address_jump;
    logic [31:0] register_save_jump;

    ram_controller ram_controller(
        clk,
        program_counter,
        instruction,
        decoded_instr.func3,
        ram_load_address,
        ram_load_value,
        ram_store_address,
        ram_store_enabled,
        ram_store_value,
        stall,
        ram_trap
    );

    pc pc(
        clk,
        pc_reset,
        reset_address,
        stall,
        program_counter
    );

    instruction_decoder instruction_decoder(
        instruction,
        decoded_instr,
        instruction_trap,
        clk,
        program_counter,
        global_counter
    );

    reg_file reg_file(
        clk,
        rs1_address,
        rs2_address,
        rs1_data,
        rs2_data,
        reg_save_enable,
        reg_save_address,
        reg_save_value
    );

    alu alu(
        clk,
        rs1_data,
        rs2_data,
        decoded_instr,
        alu_output
    );

    branch branch(
        rs1_data,
        rs2_data,
        decoded_instr,
        program_counter,

        pc_reset_branch,
        reset_address_branch
    );

    jump jump(
        decoded_instr,
        rs1_data,
        program_counter,
        register_save_jump,
        pc_reset_address_jump,
        pc_reset_jump
    );

endmodule

Riscv_project/rtl/test_.sv
`timescale 1ns/1ns


module test_ ();

    logic clk = 0;

    wrapper wrapper(clk);

    initial begin

        $display("Begin");

        $dumpfile("wave.vcd");
        $dumpvars(0, test_);

        repeat (100) begin
            #1 clk = 1;
            #1 clk = 0;
        end

        $finish;

    end


endmodule

Riscv_project/wave.vcd
$version Generated by VerilatedVcd $end
$timescale 1ns $end
 $scope module TOP $end
  $scope module test_ $end
   $var wire 1 m clk $end
   $scope module wrapper $end
    $var wire 2 n clk [1:0] $end
    $var wire 32 o global_counter [31:0] $end
    $var wire 32 J program_counter [31:0] $end
    $var wire 32 K instruction [31:0] $end
    $var wire 199 # decoded_instr [198:0] $end
    $var wire 32 v ram_load_address [31:0] $end
    $var wire 32 p ram_load_value [31:0] $end
    $var wire 32 * ram_store_address [31:0] $end
    $var wire 1 + ram_store_enabled [0:0] $end
    $var wire 32 , ram_store_value [31:0] $end
    $var wire 5 - rs1_address [4:0] $end
    $var wire 5 . rs2_address [4:0] $end
    $var wire 32 / rs1_data [31:0] $end
    $var wire 32 , rs2_data [31:0] $end
    $var wire 1 0 reg_save_enable [0:0] $end
    $var wire 5 1 reg_save_address [4:0] $end
    $var wire 32 q reg_save_value [31:0] $end
    $var wire 32 2 alu_output [31:0] $end
    $var wire 1 w stall [0:0] $end
    $var wire 1 x ram_trap [0:0] $end
    $var wire 1 3 instruction_trap [0:0] $end
    $var wire 1 4 pc_reset [0:0] $end
    $var wire 32 r reset_address [31:0] $end
    $var wire 1 5 pc_reset_branch [0:0] $end
    $var wire 32 6 reset_address_branch [31:0] $end
    $var wire 1 7 pc_reset_jump [0:0] $end
    $var wire 32 s pc_reset_address_jump [31:0] $end
    $var wire 32 t register_save_jump [31:0] $end
    $scope module alu $end
     $var wire 1 m clk [0:0] $end
     $var wire 32 / rs1 [31:0] $end
     $var wire 32 , rs2 [31:0] $end
     $var wire 199 # instr [198:0] $end
     $var wire 32 2 result [31:0] $end
     $scope module unnamedblk1 $end
      $var wire 32 8 rs1_x [31:0] $end
      $var wire 32 9 rs2_x [31:0] $end
     $upscope $end
    $upscope $end
    $scope module branch $end
     $var wire 32 / rs1_data [31:0] $end
     $var wire 32 , rs2_data [31:0] $end
     $var wire 199 # instr [198:0] $end
     $var wire 32 J pc [31:0] $end
     $var wire 1 5 pc_reset_branch [0:0] $end
     $var wire 32 6 reset_address [31:0] $end
     $scope module unnamedblk1 $end
      $var wire 32 : rs1_data_unsigned [31:0] $end
      $var wire 32 ; rs2_data_unsigned [31:0] $end
     $upscope $end
    $upscope $end
    $scope module instruction_decoder $end
     $var wire 32 K instruction [31:0] $end
     $var wire 199 # mask [198:0] $end
     $var wire 1 3 trap_instr [0:0] $end
     $var wire 1 m clk [0:0] $end
     $var wire 32 J pc [31:0] $end
     $var wire 32 o global_counter [31:0] $end
     $scope module unnamedblk1 $end
      $var wire 7 < opcode [6:0] $end
      $var wire 5 = rd [11:7] $end
      $var wire 3 > func3 [14:12] $end
      $var wire 5 ? rs1 [19:15] $end
      $var wire 5 @ rs2 [24:20] $end
      $var wire 7 A func7 [31:25] $end
      $var wire 1 B is_r [0:0] $end
      $var wire 1 C is_i [0:0] $end
      $var wire 1 D is_s [0:0] $end
      $var wire 1 E is_b [0:0] $end
      $var wire 1 F is_u [0:0] $end
      $var wire 1 G is_j [0:0] $end
     $upscope $end
    $upscope $end
    $scope module jump $end
     $var wire 199 # instr [198:0] $end
     $var wire 32 / rs1_data [31:0] $end
     $var wire 32 J program_counter [31:0] $end
     $var wire 32 t reg_save_value [31:0] $end
     $var wire 32 s pc_save_value [31:0] $end
     $var wire 1 7 pc_reset_jump [0:0] $end
    $upscope $end
    $scope module pc $end
     $var wire 1 m clk [0:0] $end
     $var wire 1 4 reset [0:0] $end
     $var wire 32 r reset_address [31:0] $end
     $var wire 1 w stall [0:0] $end
     $var wire 32 J program_counter [31:0] $end
     $var wire 32 u current_counter [31:0] $end
    $upscope $end
    $scope module ram_controller $end
     $var wire 1 m clk [0:0] $end
     $var wire 32 J pc [31:0] $end
     $var wire 32 K instruction [31:0] $end
     $var wire 3 H func3 [2:0] $end
     $var wire 32 v load_address [31:0] $end
     $var wire 32 p load_value [31:0] $end
     $var wire 32 * store_address [31:0] $end
     $var wire 1 + store_enabled [0:0] $end
     $var wire 32 , store_value [31:0] $end
     $var wire 1 w stall [0:0] $end
     $var wire 1 x trap_ram [0:0] $end
     $var wire 10 L pc_idx [9:0] $end
     $var wire 10 y store_idx [9:0] $end
     $var wire 10 I load_idx [9:0] $end
    $upscope $end
    $scope module reg_file $end
     $var wire 1 m clk [0:0] $end
     $var wire 5 - rs1_address [4:0] $end
     $var wire 5 . rs2_address [4:0] $end
     $var wire 32 / rs1_data [31:0] $end
     $var wire 32 , rs2_data [31:0] $end
     $var wire 1 0 save_enable [0:0] $end
     $var wire 5 1 save_address [4:0] $end
     $var wire 32 q save_value [31:0] $end
     $var wire 32 M block[0] [31:0] $end
     $var wire 32 N block[1] [31:0] $end
     $var wire 32 O block[2] [31:0] $end
     $var wire 32 P block[3] [31:0] $end
     $var wire 32 Q block[4] [31:0] $end
     $var wire 32 R block[5] [31:0] $end
     $var wire 32 S block[6] [31:0] $end
     $var wire 32 T block[7] [31:0] $end
     $var wire 32 U block[8] [31:0] $end
     $var wire 32 V block[9] [31:0] $end
     $var wire 32 W block[10] [31:0] $end
     $var wire 32 X block[11] [31:0] $end
     $var wire 32 Y block[12] [31:0] $end
     $var wire 32 Z block[13] [31:0] $end
     $var wire 32 [ block[14] [31:0] $end
     $var wire 32 \ block[15] [31:0] $end
     $var wire 32 ] block[16] [31:0] $end
     $var wire 32 ^ block[17] [31:0] $end
     $var wire 32 _ block[18] [31:0] $end
     $var wire 32 ` block[19] [31:0] $end
     $var wire 32 a block[20] [31:0] $end
     $var wire 32 b block[21] [31:0] $end
     $var wire 32 c block[22] [31:0] $end
     $var wire 32 d block[23] [31:0] $end
     $var wire 32 e block[24] [31:0] $end
     $var wire 32 f block[25] [31:0] $end
     $var wire 32 g block[26] [31:0] $end
     $var wire 32 h block[27] [31:0] $end
     $var wire 32 i block[28] [31:0] $end
     $var wire 32 j block[29] [31:0] $end
     $var wire 32 k block[30] [31:0] $end
     $var wire 32 l block[31] [31:0] $end
    $upscope $end
   $upscope $end
  $upscope $end
 $upscope $end
$enddefinitions $end


#0
b0110111000100000000000001000000000000000000000000000000000000001000000000000000000000000000000100000000000000000000000000000001000000000000100000000000000000000000000000000000000001000000000000000100 #
b00000000000000000000000000000010 *
0+
b00000000000000000000000000000000 ,
b00000 -
b00001 .
b00000000000000000000000000000000 /
10
b00010 1
b00000000000000000000000000000001 2
03
04
05
b00000000000000000000000000000000 6
07
b00000000000000000000000000000000 8
b00000000000000000000000000000001 9
b00000000000000000000000000000000 :
b00000000000000000000000000000000 ;
b0110111 <
b00010 =
b000 >
b00000 ?
b00001 @
b0000000 A
0B
0C
0D
0E
1F
0G
b000 H
b0000000000 I
b00000000000000000000000000000000 J
b00000000000100000000000100110111 K
b0000000000 L
b00000000000000000000000000000000 M
b00000000000000000000000000000000 N
b00000000000000000000000000000000 O
b00000000000000000000000000000000 P
b00000000000000000000000000000000 Q
b00000000000000000000000000000000 R
b00000000000000000000000000000000 S
b00000000000000000000000000000000 T
b00000000000000000000000000000000 U
b00000000000000000000000000000000 V
b00000000000000000000000000000000 W
b00000000000000000000000000000000 X
b00000000000000000000000000000000 Y
b00000000000000000000000000000000 Z
b00000000000000000000000000000000 [
b00000000000000000000000000000000 \
b00000000000000000000000000000000 ]
b00000000000000000000000000000000 ^
b00000000000000000000000000000000 _
b00000000000000000000000000000000 `
b00000000000000000000000000000000 a
b00000000000000000000000000000000 b
b00000000000000000000000000000000 c
b00000000000000000000000000000000 d
b00000000000000000000000000000000 e
b00000000000000000000000000000000 f
b00000000000000000000000000000000 g
b00000000000000000000000000000000 h
b00000000000000000000000000000000 i
b00000000000000000000000000000000 j
b00000000000000000000000000000000 k
b00000000000000000000000000000000 l
0m
b00 n
b00000000000000000000000000000000 o
b00000000000100000000000100110111 p
b00000000000100000000000000000000 q
b00000000000000000000000000000000 r
b00000000000000000000000000000000 s
b00000000000000000000000000000000 t
b00000000000000000000000000000000 u
b00000000000000000000000000000000 v
0w
0x
b0000000000 y
#1
b00000000000100000000000000000000 O
1m
b01 n
b00000000000000000000000000000100 o
#2
0m
b00 n
b00000000000000000000000000000100 u
#3
b0010111000010000000000000000000000000000000000000000000000000000000000000000000000000000000000010000000000000000000010000000000000000000000000000000000000000000000000000000000000000000000000000000100 #
b00000000000000000000000000000001 *
b00000 .
b00001 1
b00000000000000000000000000000000 2
b00000000000000000000000000000000 9
b0010111 <
b00001 =
b00000 @
b00000000000000000000000000000100 J
b00000000000000000000000010010111 K
b0000000001 L
1m
b01 n
b00000000000000000000000000001000 o
b00000000000000000000000000000100 q
#4
0m
b00 n
b00000000000000000000000000001000 u
#5
b1100111000010000000101100000000000000000000000000000000000001100000000000000000000000000000000010000000000000000000010000000000000000000110000001000000000000000000000000000000010000000000011000000001 #
b00000000000000000000000000000101 *
b00001 -
b01100 .
b00000000000000000000000000000100 /
b00000000000000000000000000010000 2
14
17
b00000000000000000000000000000100 8
b00000000000000000000000000001100 9
b00000000000000000000000000000100 :
b1100111 <
b00001 ?
b01100 @
0F
b0000000001 I
b00000000000000000000000000001000 J
b00000000110000001000000011100111 K
b0000000010 L
b00000000000000000000000000000100 N
1m
b01 n
b00000000000000000000000000001100 o
b00000000000000000000000010010111 p
b00000000000000000000000000001100 q
b00000000000000000000000000010000 r
b00000000000000000000000000010000 s
b00000000000000000000000000001100 t
#6
0m
b00 n
b00000000000000000000000000010000 u
#7
b0010011000100000001010000111111111111111111111111111111111110000111111111111111111111111111000101111111111111111111101111110001011111111000000010000000000000000111111111111000100000111111100000100000 #
b00000000000011111111111111100010 *
b00010 -
b10000 .
b00000000000100000000000000000000 /
b00010 1
b00000000000011111111111111110000 2
04
07
b00000000000100000000000000000000 8
b11111111111111111111111111110000 9
b00000000000100000000000000000000 :
b0010011 <
b00010 =
b00010 ?
b10000 @
b1111111 A
1C
b1111111000 I
b00000000000000000000000000010000 J
b11111111000000010000000100010011 K
b0000000100 L
b00000000000000000000000000001100 N
1m
b01 n
b00000000000000000000000000010000 o
b00000000000000000000000000000000 p
b00000000000011111111111111110000 q
b00000000000000000000000000000000 r
b00000000000000000000000000000000 s
b00000000000000000000000000000000 t
#8
0m
b00 n
b00000000000000000000000000010100 u
#9
b0100011011000100001000000000000000000000000000000000000000000000000000000000000000000000000011000000000000000000000000000000110000000000000000010010000000000000000000000000000100100000000000000010000 #
b00000000000011111111111111111100 *
1+
b00000 .
b00000000000011111111111111110000 /
00
b01100 1
b00000000000000000000000000000000 2
b00000000000011111111111111110000 8
b00000000000000000000000000000000 9
b00000000000011111111111111110000 :
b0100011 <
b01100 =
b010 >
b00000 @
b0000000 A
0C
1D
b010 H
b1111111111 I
b00000000000000000000000000010100 J
b00000000000000010010011000100011 K
b0000000101 L
b00000000000011111111111111110000 O
1m
b01 n
b00000000000000000000000000010100 o
b00000000000000000000000000000000 q
#10
0m
b00 n
b00000000000000000000000000011000 u
#11
b0010011011100000000001010000000000000000000000000000000000001010000000000000000000000000000011100000000000000000000000000000111000000000101000000000000000000000000000000000000000000000000010100100000 #
b00000000000000000000000000001110 *
0+
b00000 -
b01010 .
b00000000000000000000000000000000 /
10
b01110 1
b00000000000000000000000000001010 2
b00000000000000000000000000000000 8
b00000000000000000000000000001010 9
b00000000000000000000000000000000 :
b0010011 <
b01110 =
b000 >
b00000 ?
b01010 @
1C
0D
b000 H
b0000000011 I
b00000000000000000000000000011000 J
b00000000101000000000011100010011 K
b0000000110 L
1m
b01 n
b00000000000000000000000000011000 o
b00000000000000000000000001101111 p
b00000000000000000000000000001010 q
#12
0m
b00 n
b00000000000000000000000000011100 u
#13
b0000011011110100001001100000000000000000000000000000000000001100000000000000000000000000000011110000000000000000000010000000111000000000110000010010000000000000000000000000000100100000000011000100000 #
b00000000000011111111111111111111 *
b00010 -
b01100 .
b00000000000011111111111111110000 /
b01111 1
b00000000000000000000000000000000 2
b00000000000011111111111111110000 8
b00000000000000000000000000001100 9
b00000000000011111111111111110000 :
b0000011 <
b01111 =
b010 >
b00010 ?
b01100 @
b010 H
b1111111111 I
b00000000000000000000000000011100 J
b00000000110000010010011110000011 K
b0000000111 L
b00000000000000000000000000001010 [
1m
b01 n
b00000000000000000000000000011100 o
b00000000000000000000000000000000 p
b00000000000000000000000000000000 q
#14
0m
b00 n
b00000000000000000000000000100000 u
#15
b0010011011100000111011111111111111111111111111111111111111111111111111111111111111111111111011101111111111111111111101111110111011111111111101110000000000000000111111111111011100001111111111100100000 #
b11111111111111111111111111111000 *
b01110 -
b11111 .
b00000000000000000000000000001010 /
b01110 1
b00000000000000000000000000001001 2
b00000000000000000000000000001010 8
b11111111111111111111111111111111 9
b00000000000000000000000000001010 :
b0010011 <
b01110 =
b000 >
b01110 ?
b11111 @
b1111111 A
b000 H
b1111111110 I
b00000000000000000000000000100000 J
b11111111111101110000011100010011 K
b0000001000 L
1m
b01 n
b00000000000000000000000000100000 o
b00000000000000000000000000001001 q
#16
0m
b00 n
b00000000000000000000000000100100 u
#17
b0010011011110000111100001000000000000000000000000000000000000001000000000000000000000000000011110000000000000000000010000000111000000000000101111000000000000000000000000000011110001000000000000100000 #
b00000000000000000000000000001111 *
b00000000000000000000000000001100 ,
b01111 -
b00001 .
b00000000000000000000000000000000 /
b01111 1
b00000000000000000000000000000001 2
b00000000000000000000000000000000 8
b00000000000000000000000000000001 9
b00000000000000000000000000000000 :
b00000000000000000000000000001100 ;
b01111 =
b01111 ?
b00001 @
b0000000 A
b0000000011 I
b00000000000000000000000000100100 J
b00000000000101111000011110010011 K
b0000001001 L
b00000000000000000000000000001001 [
1m
b01 n
b00000000000000000000000000100100 o
b00000000000000000000000001101111 p
b00000000000000000000000000000001 q
#18
0m
b00 n
b00000000000000000000000000101000 u
#19
b0100011011000100001001111000000000000000000000000000000000001111000000000000000000000000000011000000000000000000000000000000110000000000111100010010000000000000000000000000000100101000000011100010000 #
b00000000000011111111111111111100 *
1+
b00000000000000000000000000000001 ,
b00010 -
b01111 .
b00000000000011111111111111110000 /
00
b01100 1
b00000000000000000000000000000000 2
b00000000000011111111111111110000 8
b00000000000000000000000000001111 9
b00000000000011111111111111110000 :
b00000000000000000000000000000001 ;
b0100011 <
b01100 =
b010 >
b00010 ?
b01111 @
0C
1D
b010 H
b1111111111 I
b00000000000000000000000000101000 J
b00000000111100010010011000100011 K
b0000001010 L
b00000000000000000000000000000001 \
1m
b01 n
b00000000000000000000000000101000 o
b00000000000000000000000000000000 p
b00000000000000000000000000000000 q
#20
0m
b00 n
b00000000000000000000000000101100 u
#21
b1100011100010010111000000111111111111111111111111111111111100000111111111111111111111111111100011111111111111111111111111111000011111110000001110001000000000000111111111111011100010111111000000001000 #
b11111111111111111111111111111010 *
0+
b00000000000000000000000000000000 ,
b01110 -
b00000 .
b00000000000000000000000000001001 /
b10001 1
b00000000000000000000000000001001 2
14
15
b00000000000000000000000000011100 6
b00000000000000000000000000001001 8
b00000000000000000000000000000000 9
b00000000000000000000000000001001 :
b00000000000000000000000000000000 ;
b1100011 <
b10001 =
b001 >
b01110 ?
b00000 @
b1111111 A
0D
1E
b001 H
b1111111110 I
b00000000000000000000000000101100 J
b11111110000001110001100011100011 K
b0000001011 L
1m
b01 n
b00000000000000000000000000101100 o
b00000000000000000000000000011100 r
#22
0m
b00 n
b00000000000000000000000000011100 u
#23
b0000011011110100001001100000000000000000000000000000000000001100000000000000000000000000000011110000000000000000000010000000111000000000110000010010000000000000000000000000000100100000000011000100000 #
b00000000000011111111111111111111 *
b00010 -
b01100 .
b00000000000011111111111111110000 /
10
b01111 1
b00000000000000000000000000000000 2
04
05
b00000000000000000000000000000000 6
b00000000000011111111111111110000 8
b00000000000000000000000000001100 9
b00000000000011111111111111110000 :
b0000011 <
b01111 =
b010 >
b00010 ?
b01100 @
b0000000 A
1C
0E
b010 H
b1111111111 I
b00000000000000000000000000011100 J
b00000000110000010010011110000011 K
b0000000111 L
1m
b01 n
b00000000000000000000000000110000 o
b00000000000000000000000000000000 r
#24
0m
b00 n
b00000000000000000000000000100000 u
#25
b0010011011100000111011111111111111111111111111111111111111111111111111111111111111111111111011101111111111111111111101111110111011111111111101110000000000000000111111111111011100001111111111100100000 #
b11111111111111111111111111110111 *
b01110 -
b11111 .
b00000000000000000000000000001001 /
b01110 1
b00000000000000000000000000001000 2
b00000000000000000000000000001001 8
b11111111111111111111111111111111 9
b00000000000000000000000000001001 :
b0010011 <
b01110 =
b000 >
b01110 ?
b11111 @
b1111111 A
b000 H
b1111111101 I
b00000000000000000000000000100000 J
b11111111111101110000011100010011 K
b0000001000 L
b00000000000000000000000000000000 \
1m
b01 n
b00000000000000000000000000110100 o
b00000000000000000000000000001000 q
#26
0m
b00 n
b00000000000000000000000000100100 u
#27
b0010011011110000111100001000000000000000000000000000000000000001000000000000000000000000000011110000000000000000000010000000111000000000000101111000000000000000000000000000011110001000000000000100000 #
b00000000000000000000000000001111 *
b00000000000000000000000000001100 ,
b01111 -
b00001 .
b00000000000000000000000000000000 /
b01111 1
b00000000000000000000000000000001 2
b00000000000000000000000000000000 8
b00000000000000000000000000000001 9
b00000000000000000000000000000000 :
b00000000000000000000000000001100 ;
b01111 =
b01111 ?
b00001 @
b0000000 A
b0000000011 I
b00000000000000000000000000100100 J
b00000000000101111000011110010011 K
b0000001001 L
b00000000000000000000000000001000 [
1m
b01 n
b00000000000000000000000000111000 o
b00000000000000000000000001101111 p
b00000000000000000000000000000001 q
#28
0m
b00 n
b00000000000000000000000000101000 u
#29
b0100011011000100001001111000000000000000000000000000000000001111000000000000000000000000000011000000000000000000000000000000110000000000111100010010000000000000000000000000000100101000000011100010000 #
b00000000000011111111111111111100 *
1+
b00000000000000000000000000000001 ,
b00010 -
b01111 .
b00000000000011111111111111110000 /
00
b01100 1
b00000000000000000000000000000000 2
b00000000000011111111111111110000 8
b00000000000000000000000000001111 9
b00000000000011111111111111110000 :
b00000000000000000000000000000001 ;
b0100011 <
b01100 =
b010 >
b00010 ?
b01111 @
0C
1D
b010 H
b1111111111 I
b00000000000000000000000000101000 J
b00000000111100010010011000100011 K
b0000001010 L
b00000000000000000000000000000001 \
1m
b01 n
b00000000000000000000000000111100 o
b00000000000000000000000000000000 p
b00000000000000000000000000000000 q
#30
0m
b00 n
b00000000000000000000000000101100 u
